MANIFEST.in
README.rst
setup.py
aliyun_python_sdk_domain_intl.egg-info/PKG-INFO
aliyun_python_sdk_domain_intl.egg-info/SOURCES.txt
aliyun_python_sdk_domain_intl.egg-info/dependency_links.txt
aliyun_python_sdk_domain_intl.egg-info/requires.txt
aliyun_python_sdk_domain_intl.egg-info/top_level.txt
aliyunsdkdomain_intl/__init__.py
aliyunsdkdomain_intl/request/__init__.py
aliyunsdkdomain_intl/request/v20171218/AcknowledgeTaskResultRequest.py
aliyunsdkdomain_intl/request/v20171218/BatchFuzzyMatchDomainSensitiveWordRequest.py
aliyunsdkdomain_intl/request/v20171218/CancelDomainVerificationRequest.py
aliyunsdkdomain_intl/request/v20171218/CancelTaskRequest.py
aliyunsdkdomain_intl/request/v20171218/CheckDomainRequest.py
aliyunsdkdomain_intl/request/v20171218/CheckDomainSunriseClaimRequest.py
aliyunsdkdomain_intl/request/v20171218/CheckTransferInFeasibilityRequest.py
aliyunsdkdomain_intl/request/v20171218/ConfirmTransferInEmailRequest.py
aliyunsdkdomain_intl/request/v20171218/DeleteEmailVerificationRequest.py
aliyunsdkdomain_intl/request/v20171218/DeleteRegistrantProfileRequest.py
aliyunsdkdomain_intl/request/v20171218/EmailVerifiedRequest.py
aliyunsdkdomain_intl/request/v20171218/FuzzyMatchDomainSensitiveWordRequest.py
aliyunsdkdomain_intl/request/v20171218/ListEmailVerificationRequest.py
aliyunsdkdomain_intl/request/v20171218/LookupTmchNoticeRequest.py
aliyunsdkdomain_intl/request/v20171218/PollTaskResultRequest.py
aliyunsdkdomain_intl/request/v20171218/QueryArtExtensionRequest.py
aliyunsdkdomain_intl/request/v20171218/QueryChangeLogListRequest.py
aliyunsdkdomain_intl/request/v20171218/QueryContactInfoRequest.py
aliyunsdkdomain_intl/request/v20171218/QueryDSRecordRequest.py
aliyunsdkdomain_intl/request/v20171218/QueryDnsHostRequest.py
aliyunsdkdomain_intl/request/v20171218/QueryDomainByDomainNameRequest.py
aliyunsdkdomain_intl/request/v20171218/QueryDomainByInstanceIdRequest.py
aliyunsdkdomain_intl/request/v20171218/QueryDomainListRequest.py
aliyunsdkdomain_intl/request/v20171218/QueryDomainRealNameVerificationInfoRequest.py
aliyunsdkdomain_intl/request/v20171218/QueryEnsAssociationRequest.py
aliyunsdkdomain_intl/request/v20171218/QueryFailReasonForDomainRealNameVerificationRequest.py
